airflow_notify_sns/__init__.py
airflow_notify_sns/notify.py
cog_airflow_notify_sns-2.0.8.dist-info/LICENSE
cog_airflow_notify_sns-2.0.8.dist-info/METADATA
cog_airflow_notify_sns-2.0.8.dist-info/WHEEL
cog_airflow_notify_sns-2.0.8.dist-info/top_level.txt
cog_airflow_notify_sns-2.0.8.dist-info/RECORD
