Metadata-Version: 2.1
Name: cog-airflow-notify-sns
Version: 2.0.8
Summary: Publish Airflow notification errors to SNS Topic
Home-page: https://github.com/cognitivo/cog.dataplatform.service.system.airflow.notification
Author: Cognitivo.ai
Author-email: engenharia@cognitivo.ai
Classifier: Programming Language :: Python :: 3
Classifier: License :: OSI Approved :: MIT License
Classifier: Operating System :: OS Independent
License-File: LICENSE
